jupyter_server_terminals/__init__.py
jupyter_server_terminals/_version.py
jupyter_server_terminals/api_handlers.py
jupyter_server_terminals/app.py
jupyter_server_terminals/base.py
jupyter_server_terminals/handlers.py
jupyter_server_terminals/rest-api.yml
jupyter_server_terminals/terminalmanager.py
jupyter_server_terminals-0.4.1.data/data/etc/jupyter/jupyter_server_config.d/jupyter_server_terminals.json
jupyter_server_terminals-0.4.1.dist-info/METADATA
jupyter_server_terminals-0.4.1.dist-info/WHEEL
jupyter_server_terminals-0.4.1.dist-info/licenses/LICENSE
jupyter_server_terminals-0.4.1.dist-info/RECORD
