Metadata-Version: 2.1
Name: jupyter_server_terminals
Version: 0.4.1
Summary: A Jupyter Server Extension Providing Terminals.
Project-URL: Homepage, https://jupyter.org
Author-email: Jupyter Development Team <jupyter@googlegroups.com>
License: # Licensing terms
License-File: LICENSE
Keywords: ipython,jupyter
Classifier: Intended Audience :: Developers
Classifier: Intended Audience :: Science/Research
Classifier: Intended Audience :: System Administrators
Classifier: License :: OSI Approved :: BSD License
Classifier: Programming Language :: Python
Classifier: Programming Language :: Python :: 3.7
Classifier: Programming Language :: Python :: 3.8
Classifier: Programming Language :: Python :: 3.9
Classifier: Programming Language :: Python :: 3.10
Requires-Python: >=3.8
Requires-Dist: pywinpty>=2.0.3; os_name == 'nt'
Requires-Dist: terminado>=0.8.3
Provides-Extra: docs
Requires-Dist: jinja2; extra == 'docs'
Requires-Dist: jupyter-server; extra == 'docs'
Requires-Dist: mistune<2.0; extra == 'docs'
Requires-Dist: myst-parser; extra == 'docs'
Requires-Dist: nbformat; extra == 'docs'
Requires-Dist: packaging; extra == 'docs'
Requires-Dist: pydata-sphinx-theme; extra == 'docs'
Requires-Dist: sphinxcontrib-github-alt; extra == 'docs'
Requires-Dist: sphinxcontrib-openapi; extra == 'docs'
Requires-Dist: sphinxemoji; extra == 'docs'
Requires-Dist: tornado; extra == 'docs'
Provides-Extra: test
Requires-Dist: coverage; extra == 'test'
Requires-Dist: jupyter-server[test]>=2.0.0rc5; extra == 'test'
Requires-Dist: pytest-cov; extra == 'test'
Requires-Dist: pytest-timeout; extra == 'test'
Requires-Dist: pytest-tornasync; extra == 'test'
Requires-Dist: pytest>=7.0; extra == 'test'
